{"verbs":[{"verb_id":146,"u_id":1,"f_id":4,"form":"x-y-z","inf":"to spring","pret":"sprang","part":"sprung","tran":"jaillir, bondir","usage":"common","url":"https://translate.google.com/translate_tts?ie=UTF-8&tl=en&client=tw-ob&q=\"to%20spring,sprang,sprung\"","alt_of":false},{"verb_id":101,"u_id":2,"f_id":4,"form":"x-y-z","inf":"to ring","pret":"rang","part":"rung","tran":"sonner","usage":"overused","url":"https://translate.google.com/translate_tts?ie=UTF-8&tl=en&client=tw-ob&q=\"to%20ring,rang,rung\"","alt_of":false},{"verb_id":122,"u_id":1,"f_id":4,"form":"x-y-z","inf":"to shrink","pret":"shrank","part":"shrunk","tran":"rétrécir","usage":"common","url":"https://translate.google.com/translate_tts?ie=UTF-8&tl=en&client=tw-ob&q=\"to%20shrink,shrank,shrunk\"","alt_of":false},{"verb_id":8,"u_id":2,"f_id":4,"form":"x-y-z","inf":"to begin","pret":"began","part":"begun","tran":"commencer","usage":"overused","url":"https://translate.google.com/translate_tts?ie=UTF-8&tl=en&client=tw-ob&q=\"to%20begin,began,begun\"","alt_of":false},{"verb_id":5,"u_id":1,"f_id":4,"form":"x-y-z","inf":"to bear","pret":"bore","part":"borne","tran":"supporter","usage":"common","url":"https://translate.google.com/translate_tts?ie=UTF-8&tl=en&client=tw-ob&q=\"to%20bear,bore,borne\"","alt_of":false},{"verb_id":156,"u_id":1,"f_id":4,"form":"x-y-z","inf":"to swear","pret":"swore","part":"sworn","tran":"jurer","usage":"common","url":"https://translate.google.com/translate_tts?ie=UTF-8&tl=en&client=tw-ob&q=\"to%20swear,swore,sworn\"","alt_of":false},{"verb_id":159,"u_id":2,"f_id":4,"form":"x-y-z","inf":"to swim","pret":"swam","part":"swum","tran":"nager","usage":"overused","url":"https://translate.google.com/translate_tts?ie=UTF-8&tl=en&client=tw-ob&q=\"to%20swim,swam,swum\"","alt_of":false},{"verb_id":127,"u_id":1,"f_id":4,"form":"x-y-z","inf":"to slay","pret":"slew","part":"slain","tran":"assassiner","usage":"common","url":"https://translate.google.com/translate_tts?ie=UTF-8&tl=en&client=tw-ob&q=\"to%20slay,slew,slain\"","alt_of":false},{"verb_id":51,"u_id":2,"f_id":4,"form":"x-y-z","inf":"to fly","pret":"flew","part":"flown","tran":"voler","usage":"overused","url":"https://translate.google.com/translate_tts?ie=UTF-8&tl=en&client=tw-ob&q=\"to%20fly,flew,flown\"","alt_of":false},{"verb_id":114,"u_id":1,"f_id":4,"form":"x-y-z","inf":"to shear","pret":"sheared","part":"shorn","tran":"tondre- cisailler","usage":"common","url":"https://translate.google.com/translate_tts?ie=UTF-8&tl=en&client=tw-ob&q=\"to%20shear,sheared,shorn\"","alt_of":false},{"verb_id":4,"u_id":2,"f_id":4,"form":"x-y-z","inf":"to be","pret":"was","part":"been","tran":"être","usage":"overused","url":"https://translate.google.com/translate_tts?ie=UTF-8&tl=en&client=tw-ob&q=\"to%20be,was,been\"","alt_of":false},{"verb_id":171,"u_id":3,"f_id":4,"form":"x-y-z","inf":"to wake (up)","pret":"woke (up)","part":"waked (up)","tran":"se réveiller","usage":"rare","url":"https://translate.google.com/translate_tts?ie=UTF-8&tl=en&client=tw-ob&q=\"to%20wake (up),woke (up),waked (up)\"","alt_of":true},{"verb_id":151,"u_id":1,"f_id":4,"form":"x-y-z","inf":"to stink","pret":"stank","part":"stunk","tran":"puer","usage":"common","url":"https://translate.google.com/translate_tts?ie=UTF-8&tl=en&client=tw-ob&q=\"to%20stink,stank,stunk\"","alt_of":false},{"verb_id":124,"u_id":2,"f_id":4,"form":"x-y-z","inf":"to sing","pret":"sang","part":"sung","tran":"chanter","usage":"overused","url":"https://translate.google.com/translate_tts?ie=UTF-8&tl=en&client=tw-ob&q=\"to%20sing,sang,sung\"","alt_of":false},{"verb_id":125,"u_id":1,"f_id":4,"form":"x-y-z","inf":"to sink","pret":"sank","part":"sunk","tran":"couler","usage":"common","url":"https://translate.google.com/translate_tts?ie=UTF-8&tl=en&client=tw-ob&q=\"to%20sink,sank,sunk\"","alt_of":false},{"verb_id":38,"u_id":2,"f_id":4,"form":"x-y-z","inf":"to drink","pret":"drank","part":"drunk","tran":"boire","usage":"overused","url":"https://translate.google.com/translate_tts?ie=UTF-8&tl=en&client=tw-ob&q=\"to%20drink,drank,drunk\"","alt_of":false},{"verb_id":84,"u_id":1,"f_id":4,"form":"x-y-z","inf":"to lie","pret":"lay","part":"lain","tran":"être étendu","usage":"common","url":"https://translate.google.com/translate_tts?ie=UTF-8&tl=en&client=tw-ob&q=\"to%20lie,lay,lain\"","alt_of":false},{"verb_id":163,"u_id":1,"f_id":4,"form":"x-y-z","inf":"to tear","pret":"tore","part":"torn","tran":"déchirer","usage":"common","url":"https://translate.google.com/translate_tts?ie=UTF-8&tl=en&client=tw-ob&q=\"to%20tear,tore,torn\"","alt_of":false},{"verb_id":172,"u_id":2,"f_id":4,"form":"x-y-z","inf":"to wear","pret":"wore","part":"worn","tran":"porter (des habits)","usage":"overused","url":"https://translate.google.com/translate_tts?ie=UTF-8&tl=en&client=tw-ob&q=\"to%20wear,wore,worn\"","alt_of":false}]}